runway_mcp_server/__init__.py
runway_mcp_server/server.py
runway_mcp_server-0.1.0.dist-info/METADATA
runway_mcp_server-0.1.0.dist-info/WHEEL
runway_mcp_server-0.1.0.dist-info/entry_points.txt
runway_mcp_server-0.1.0.dist-info/top_level.txt
runway_mcp_server-0.1.0.dist-info/RECORD
