Metadata-Version: 2.4
Name: runway-mcp-server
Version: 0.1.0
Summary: MCP server for Runway ML video generation with Gen-4, Veo 3, Aleph video editing, and comprehensive AI video tools
Author-email: Sid <your-email@example.com>
License: MIT
Project-URL: Homepage, https://github.com/sidart10/runway-mcp-server
Project-URL: Documentation, https://github.com/sidart10/runway-mcp-server#readme
Project-URL: Repository, https://github.com/sidart10/runway-mcp-server
Project-URL: Issues, https://github.com/sidart10/runway-mcp-server/issues
Project-URL: Runway Developer Portal, https://dev.runwayml.com
Keywords: mcp,model-context-protocol,runway,ai-video,video-generation,gen-4,aleph,video-editing,veo,ai
Classifier: Development Status :: 4 - Beta
Classifier: Intended Audience :: Developers
Classifier: Topic :: Software Development :: Libraries :: Python Modules
Classifier: Topic :: Multimedia :: Video
Classifier: Topic :: Scientific/Engineering :: Artificial Intelligence
Classifier: Programming Language :: Python :: 3
Classifier: Programming Language :: Python :: 3.10
Classifier: Programming Language :: Python :: 3.11
Classifier: Programming Language :: Python :: 3.12
Classifier: License :: OSI Approved :: MIT License
Classifier: Operating System :: OS Independent
Requires-Python: >=3.10
Requires-Dist: mcp>=1.2.0
Requires-Dist: runwayml>=0.3.0
Requires-Dist: httpx>=0.24.0
Requires-Dist: python-dotenv>=1.0.0
